frog_ssg/__init__.py
frog_ssg/__main__.py
frog_ssg-0.0.5.dist-info/LICENSE
frog_ssg-0.0.5.dist-info/METADATA
frog_ssg-0.0.5.dist-info/WHEEL
frog_ssg-0.0.5.dist-info/entry_points.txt
frog_ssg-0.0.5.dist-info/top_level.txt
frog_ssg-0.0.5.dist-info/RECORD
